{"data": [{"type": "Feature", "geometry": {"coordinates": [-75.54629517, -10.36002586], "type": "Point"}, "properties": {"item": "267", "visualizacion_": "SI", "tipo_alerta_": "VIGENTE", "estado": "TRANSITO RESTRINGIDO", "fecha_evento": "23/01/2023", "fecha_actualizacion": "31/01/2023 21:00 HORAS", "ubigeo": "PASCO/OXAPAMPA/HUANCABAMBA", "afectacion": "KM 80", "evento": "CONTINUA LA LIMPIEZA Y ELIMINACION DE DERRUMBE MAYOR", "latitud": "-10.36002586", "longitud": "-75.54629517", "_sort_": "-10.36002586+-75.54629517", "_fecha_actualizacion_": "2023 21:00 HORAS+01+31+21:00", "cant_vehiculos_detenidos_pasajeros": "0", "cant_vehiculos_detenidos_mercancias": "0", "fuente": "COE-MTC", "motivo": "CLIMATOLOGICO", "codigo_via": "PE-5NA", "nombre_carretera": "CARRETERA PAUCARTAMBO - OXAPAMPA - SAN JUAN DEL CODO", "alerta_activa_24_horas": "SI"}}, {"type": "Feature", "geometry": {"coordinates": [-75.183615, -14.538951], "type": "Point"}, "properties": {"item": "207", "visualizacion_": "SI", "tipo_alerta_": "VIGENTE", "estado": "TRANSITO RESTRINGIDO", "fecha_evento": "31/01/2023", "fecha_actualizacion": "31/01/2023 21:00 HORAS", "ubigeo": "ICA/PALPA/PALPA", "afectacion": "KM 400+800", "evento": "VIA AFECTADA POR EL DESBORDE DEL RIO  VISCAS", "latitud": "-14.538951", "longitud": "-75.183615", "_sort_": "-14.538951+-75.183615", "_fecha_actualizacion_": "2023 21:00 HORAS+01+31+21:00", "cant_vehiculos_detenidos_pasajeros": "15", "cant_vehiculos_detenidos_mercancias": "81", "fuente": "COMISARIA PNP PALPA", "motivo": "CLIMATOLOGICO", "codigo_via": "PE-1S", "nombre_carretera": "LONGITUDINAL DE LA COSTA  SUR", "alerta_activa_24_horas": "SI"}}]}